LICENSE
README.md
setup.py
clat/__init__.py
clat/cli.py
clat.egg-info/PKG-INFO
clat.egg-info/SOURCES.txt
clat.egg-info/dependency_links.txt
clat.egg-info/entry_points.txt
clat.egg-info/requires.txt
clat.egg-info/top_level.txt