Metadata-Version: 2.1
Name: clat
Version: 1.1
Summary: Command Line Analysis Tools: A collection of tools for doing data analysis.
Home-page: https://github.com/CD3/clat
Author: CD Clark III
License: MIT
Project-URL: Issues, https://github.com/CD3/clat/issues
Project-URL: CI, https://github.com/CD3/clat/actions
Project-URL: Changelog, https://github.com/CD3/clat/releases
Platform: UNKNOWN
Requires-Python: >=3.6
Provides-Extra: test
License-File: LICENSE
